ttfautohint_py-0.6.0.dist-info/zip-safe
ttfautohint_py-0.6.0.dist-info/RECORD
ttfautohint_py-0.6.0.dist-info/WHEEL
ttfautohint_py-0.6.0.dist-info/top_level.txt
ttfautohint_py-0.6.0.dist-info/METADATA
ttfautohint_py-0.6.0.dist-info/licenses/LICENSE
ttfautohint/options.py
ttfautohint/_version.py
ttfautohint/__init__.py
ttfautohint/ttfautohint
ttfautohint/cli.py
ttfautohint/errors.py
ttfautohint/_compat.py
ttfautohint/__main__.py
