Metadata-Version: 2.4
Name: ttfautohint-py
Version: 0.6.0
Summary: Python wrapper for ttfautohint, a free auto-hinter for TrueType fonts
Home-page: https://github.com/fonttools/ttfautohint-py
Author: Cosimo Lupo
Author-email: cosimo@anthrotype.com
License: MIT
Platform: posix
Platform: nt
Classifier: Development Status :: 5 - Production/Stable
Classifier: Environment :: Console
Classifier: Environment :: Other Environment
Classifier: Intended Audience :: Developers
Classifier: Intended Audience :: End Users/Desktop
Classifier: License :: OSI Approved :: MIT License
Classifier: Natural Language :: English
Classifier: Operating System :: OS Independent
Classifier: Programming Language :: Python
Classifier: Programming Language :: Python :: 3
Classifier: Topic :: Text Processing :: Fonts
Classifier: Topic :: Multimedia :: Graphics
Requires-Python: >=3.9
License-File: LICENSE
Provides-Extra: testing
Requires-Dist: pytest; extra == "testing"
Requires-Dist: coverage; extra == "testing"
Requires-Dist: fontTools; extra == "testing"
Dynamic: author
Dynamic: author-email
Dynamic: classifier
Dynamic: description
Dynamic: description-content-type
Dynamic: home-page
Dynamic: license
Dynamic: license-file
Dynamic: platform
Dynamic: provides-extra
Dynamic: requires-python
Dynamic: summary
